odoo/addons/product_supplierinfo_for_customer_sale/README.rst
odoo/addons/product_supplierinfo_for_customer_sale/__init__.py
odoo/addons/product_supplierinfo_for_customer_sale/__manifest__.py
odoo/addons/product_supplierinfo_for_customer_sale/i18n/de.po
odoo/addons/product_supplierinfo_for_customer_sale/i18n/it.po
odoo/addons/product_supplierinfo_for_customer_sale/i18n/product_supplierinfo_for_customer_sale.pot
odoo/addons/product_supplierinfo_for_customer_sale/models/__init__.py
odoo/addons/product_supplierinfo_for_customer_sale/models/product_product.py
odoo/addons/product_supplierinfo_for_customer_sale/models/sale.py
odoo/addons/product_supplierinfo_for_customer_sale/readme/CONTRIBUTORS.rst
odoo/addons/product_supplierinfo_for_customer_sale/readme/DESCRIPTION.rst
odoo/addons/product_supplierinfo_for_customer_sale/readme/ROADMAP.rst
odoo/addons/product_supplierinfo_for_customer_sale/readme/USAGE.rst
odoo/addons/product_supplierinfo_for_customer_sale/static/description/configuration_customer.png
odoo/addons/product_supplierinfo_for_customer_sale/static/description/description_code.png
odoo/addons/product_supplierinfo_for_customer_sale/static/description/description_code_2.png
odoo/addons/product_supplierinfo_for_customer_sale/static/description/icon.png
odoo/addons/product_supplierinfo_for_customer_sale/static/description/index.html
odoo/addons/product_supplierinfo_for_customer_sale/static/description/search_code.png
odoo/addons/product_supplierinfo_for_customer_sale/static/description/search_code_2.png
odoo/addons/product_supplierinfo_for_customer_sale/tests/__init__.py
odoo/addons/product_supplierinfo_for_customer_sale/tests/test_product_name_search.py
odoo/addons/product_supplierinfo_for_customer_sale/tests/test_product_supplierinfo_for_customer_sale.py
odoo/addons/product_supplierinfo_for_customer_sale/views/sale_view.xml
odoo11_addon_product_supplierinfo_for_customer_sale-11.0.1.0.1.dist-info/METADATA
odoo11_addon_product_supplierinfo_for_customer_sale-11.0.1.0.1.dist-info/WHEEL
odoo11_addon_product_supplierinfo_for_customer_sale-11.0.1.0.1.dist-info/top_level.txt
odoo11_addon_product_supplierinfo_for_customer_sale-11.0.1.0.1.dist-info/RECORD
